ckan_cloud_operator/__init__.py
ckan_cloud_operator/cli.py
ckan_cloud_operator/cloudflare.py
ckan_cloud_operator/datapushers.py
ckan_cloud_operator/datastore_permissions.py
ckan_cloud_operator/gcloud.py
ckan_cloud_operator/gitlab.py
ckan_cloud_operator/infra.py
ckan_cloud_operator/kubectl.py
ckan_cloud_operator/logs.py
ckan_cloud_operator/storage.py
ckan_cloud_operator/yaml_config.py
ckan_cloud_operator/annotations/__init__.py
ckan_cloud_operator/annotations/manager.py
ckan_cloud_operator/config/__init__.py
ckan_cloud_operator/config/cli.py
ckan_cloud_operator/config/manager.py
ckan_cloud_operator/crds/__init__.py
ckan_cloud_operator/crds/cli.py
ckan_cloud_operator/crds/manager.py
ckan_cloud_operator/dataflows/__init__.py
ckan_cloud_operator/dataflows/ckan_images.py
ckan_cloud_operator/dataflows/resources.py
ckan_cloud_operator/deis_ckan/__init__.py
ckan_cloud_operator/deis_ckan/annotations.py
ckan_cloud_operator/deis_ckan/ckan.py
ckan_cloud_operator/deis_ckan/datapusher.py
ckan_cloud_operator/deis_ckan/db.py
ckan_cloud_operator/deis_ckan/deployment.py
ckan_cloud_operator/deis_ckan/envvars.py
ckan_cloud_operator/deis_ckan/instance.py
ckan_cloud_operator/deis_ckan/migrate.py
ckan_cloud_operator/deis_ckan/namespace.py
ckan_cloud_operator/deis_ckan/registry.py
ckan_cloud_operator/deis_ckan/solr.py
ckan_cloud_operator/deis_ckan/spec.py
ckan_cloud_operator/deis_ckan/storage.py
ckan_cloud_operator/drivers/__init__.py
ckan_cloud_operator/drivers/postgresdbdiff.py
ckan_cloud_operator/drivers/gcloud/__init__.py
ckan_cloud_operator/drivers/gcloud/driver.py
ckan_cloud_operator/drivers/helm/__init__.py
ckan_cloud_operator/drivers/helm/cli.py
ckan_cloud_operator/drivers/helm/driver.py
ckan_cloud_operator/drivers/jenkins/__init__.py
ckan_cloud_operator/drivers/jenkins/cli.py
ckan_cloud_operator/drivers/jenkins/driver.py
ckan_cloud_operator/drivers/kubectl/__init__.py
ckan_cloud_operator/drivers/kubectl/cli.py
ckan_cloud_operator/drivers/kubectl/driver.py
ckan_cloud_operator-0.0.7.dist-info/LICENSE
ckan_cloud_operator-0.0.7.dist-info/METADATA
ckan_cloud_operator-0.0.7.dist-info/WHEEL
ckan_cloud_operator-0.0.7.dist-info/entry_points.txt
ckan_cloud_operator-0.0.7.dist-info/top_level.txt
ckan_cloud_operator-0.0.7.dist-info/RECORD
