Metadata-Version: 2.1
Name: ckan-cloud-operator
Version: 0.0.7
Summary: CKAN Cloud Kubernetes operator
Home-page: https://github.com/datopian/ckan-cloud-operator
Author: Viderum
Author-email: UNKNOWN
License: MIT
Platform: UNKNOWN
Requires-Dist: httpagentparser
Requires-Dist: boto3
Requires-Dist: coverage
Requires-Dist: psycopg2
Requires-Dist: pyyaml (<5.3,>=5)
Requires-Dist: kubernetes
Requires-Dist: click
Requires-Dist: toml
Requires-Dist: awscli
Requires-Dist: urllib3 (<1.25)
Requires-Dist: ruamel.yaml (<1)
Requires-Dist: requests (==2.21)
Requires-Dist: python-dateutil (<3)
Requires-Dist: botocore
